odoo/addons/procurement_auto_create_group_carrier/README.rst
odoo/addons/procurement_auto_create_group_carrier/__init__.py
odoo/addons/procurement_auto_create_group_carrier/__manifest__.py
odoo/addons/procurement_auto_create_group_carrier/i18n/procurement_auto_create_group_carrier.pot
odoo/addons/procurement_auto_create_group_carrier/models/__init__.py
odoo/addons/procurement_auto_create_group_carrier/models/stock_rule.py
odoo/addons/procurement_auto_create_group_carrier/readme/CONTRIBUTORS.rst
odoo/addons/procurement_auto_create_group_carrier/readme/DESCRIPTION.rst
odoo/addons/procurement_auto_create_group_carrier/static/description/icon.png
odoo/addons/procurement_auto_create_group_carrier/static/description/index.html
odoo/addons/procurement_auto_create_group_carrier/tests/__init__.py
odoo/addons/procurement_auto_create_group_carrier/tests/test_procurement_auto_create_group_carrier.py
odoo13_addon_procurement_auto_create_group_carrier-13.0.1.0.1.dev4.dist-info/METADATA
odoo13_addon_procurement_auto_create_group_carrier-13.0.1.0.1.dev4.dist-info/WHEEL
odoo13_addon_procurement_auto_create_group_carrier-13.0.1.0.1.dev4.dist-info/top_level.txt
odoo13_addon_procurement_auto_create_group_carrier-13.0.1.0.1.dev4.dist-info/RECORD
